collatex_tei/__init__.py
collatex_tei/main.py
collatex_tei-0.1.0.dist-info/LICENSE
collatex_tei-0.1.0.dist-info/METADATA
collatex_tei-0.1.0.dist-info/WHEEL
collatex_tei-0.1.0.dist-info/RECORD
